[
  {
    "name": "英歌舞",
    "category": "非遗/传统舞蹈",
    "description": "英歌舞是潮汕地区独有的传统舞蹈，表演者画着梁山好汉脸谱，手持英歌槌，随锣鼓节奏变换阵型，模仿梁山好汉攻打大名府的故事。动作刚劲有力，气势磅礴，被誉为'中华战舞'。分前棚（舞蹈）和后棚（武术对打），表演者通常36或72人。",
    "best_viewing": "春节至元宵（农历正月初一至十五），各乡里巡游",
    "region": "汕头潮阳区、潮南区、揭阳普宁",
    "level": "国家级非遗",
    "tips": "潮阳后溪英歌队、西岐英歌队最著名。站在高处观看效果最佳。"
  },
  {
    "name": "潮剧",
    "category": "非遗/传统戏剧",
    "description": "潮剧有580多年历史，属南戏分支，用潮州方言演唱。唱腔以轻六调、重六调为主，角色分生、旦、净、丑四大行当。唱腔优美、做工细腻，是潮汕文化的艺术瑰宝。",
    "best_viewing": "汕头慧如剧场、潮州潮剧团定期演出",
    "region": "潮汕全境",
    "level": "国家级非遗",
    "tips": "代表剧目：《荔镜记》（陈三五娘）、《苏六娘》、《张春郎削发》。传承人姚璇秋是潮剧泰斗。"
  },
  {
    "name": "潮汕工夫茶",
    "category": "非遗/民俗",
    "description": "潮汕工夫茶是中国茶道的'活化石'。讲究'和、敬、精、乐'四字精神。茶叶以凤凰单丛为代表，茶具讲究'四宝'：玉书煨（砂铫烧水壶）、潮汕炉（红泥小炭炉）、孟臣罐（宜兴紫砂小壶）、若琛杯（小白瓷杯）。二十一式冲泡技法极为讲究。",
    "best_viewing": "潮州古城工夫茶体验馆，凤凰镇茶园全年可体验",
    "region": "潮汕全境",
    "level": "国家级非遗",
    "tips": "主人斟茶时，客人以食指和中指轻叩桌面表示感谢（叩手礼）。第一泡茶通常倒掉（洗茶）。常用茶叶：鸭屎香、蜜兰香凤凰单丛。传承人：陈香白。"
  },
  {
    "name": "潮州音乐",
    "category": "非遗/传统音乐",
    "description": "潮州音乐形式多样：弦诗乐（以二弦为领奏的丝竹乐，优雅细腻）、笛套古乐（潮阳笛套大锣鼓，宫廷雅乐遗风）、潮州锣鼓乐（气势磅礴）。代表曲目：《寒鸦戏水》、《平沙落雁》、《昭君怨》。",
    "best_viewing": "潮汕各地庙会、节庆活动均有演奏",
    "region": "潮汕全境",
    "level": "国家级非遗",
    "tips": "主要乐器：二弦、椰胡、扬琴、琵琶。《寒鸦戏水》是必听的经典曲目。"
  },
  {
    "name": "嵌瓷",
    "category": "非遗/传统美术",
    "description": "用彩色碎瓷片在建筑屋顶、墙壁上拼贴人物花鸟等图案，色彩鲜艳、百年不掉，被称为'屋顶上的艺术'。多用于庙宇、祠堂的屋脊装饰，在阳光下熠熠生辉。潮州开元寺、己略黄公祠、汕头存心善堂都是观赏佳处。",
    "best_viewing": "潮州开元寺、己略黄公祠、汕头存心善堂，全年可观赏",
    "region": "潮州、汕头",
    "level": "国家级非遗",
    "tips": "大寮嵌瓷最著名。抬头看屋顶！人物脸部用瓷片最精细。传承人：卢芝高。"
  },
  {
    "name": "潮州木雕",
    "category": "非遗/传统美术",
    "description": "潮州木雕以多层镂空雕刻和金漆贴饰著称，可达七层透雕。题材多取自戏曲故事、历史传说和吉祥图案。金碧辉煌、工艺精湛，是中国四大木雕之一。",
    "best_viewing": "潮州己略黄公祠、揭阳关帝庙、潮州开元寺，全年可观赏",
    "region": "潮州、揭阳",
    "level": "国家级非遗",
    "tips": "己略黄公祠的木雕是'潮州木雕一绝'，值得专程去看。传承人：陈舜羌。"
  },
  {
    "name": "潮绣",
    "category": "非遗/传统美术",
    "description": "潮绣是粤绣的重要分支，以垫高绣、双面绣、钉金绣（金属线刺绣）为特色技法。'垫凸绣'在绣品下垫入棉絮，产生浮雕般的立体效果。色彩浓烈、富丽堂皇，常用于庙宇装饰和节庆服饰。",
    "best_viewing": "潮州潮绣博物馆",
    "region": "潮州",
    "level": "国家级非遗",
    "tips": "钉金绣用真金线刺绣，阳光下金光闪闪。与苏绣的清淡风格形成鲜明对比。"
  },
  {
    "name": "铁枝木偶",
    "category": "非遗/传统戏剧",
    "description": "又称'纸影戏'，表演者通过三根铁枝操控木偶，配以潮剧唱腔，在微型舞台上表演完整剧目。木偶制作精巧，被誉为'微型潮剧'，是潮汕农村节庆的重要娱乐活动。",
    "best_viewing": "潮汕农村节庆和庙会期间",
    "region": "揭阳、潮州",
    "level": "国家级非遗",
    "tips": "木偶的头部和手部最为精细。近距离观看能看到操控的巧妙。传承人：陈培森。"
  },
  {
    "name": "潮州大锣鼓",
    "category": "非遗/传统音乐",
    "description": "以大鼓为中心，配以深波、苏锣、大小钹、唢呐等多种乐器的大型打击乐合奏。气势磅礴、震撼人心。分'文套'（悠扬典雅）和'武套'（激昂热烈）。是潮汕游神赛会中最重要的配乐。",
    "best_viewing": "春节期间各村镇营老爷巡游",
    "region": "潮汕全境",
    "level": "国家级非遗",
    "tips": "武套大锣鼓最适合现场感受——鼓声震天、气势如虹。传承人：黄壮茂。"
  },
  {
    "name": "潮汕抽纱",
    "category": "非遗/传统美术",
    "description": "在棉布上抽去部分经纬线再加以刺绣的精细手工艺。通透轻盈、精细繁复，是19世纪末西洋抽纱技术与潮汕本地刺绣融合的产物。潮汕抽纱曾是重要的出口创汇产品。",
    "best_viewing": "汕头抽纱博物馆",
    "region": "汕头",
    "level": "国家级非遗",
    "tips": "细看可见抽纱的镂空花纹极为精细。一件大型抽纱作品可能需要数月甚至数年完成。"
  },
  {
    "name": "潮汕剪纸",
    "category": "非遗/传统美术",
    "description": "以精细秀丽、构图饱满著称。题材多为吉祥图案：福禄寿、龙凤呈祥、年年有余等。阳剪（留线去面）和阴剪（留面去线）两种技法，线条细如发丝。",
    "best_viewing": "潮州牌坊街非遗工坊，可体验制作",
    "region": "潮州、汕头",
    "level": "省级非遗",
    "tips": "省级传承人许舜英在潮州牌坊街开设工坊，游客可亲手体验剪纸。"
  },
  {
    "name": "出花园",
    "category": "民俗/人生礼俗",
    "description": "潮汕地区15岁成人礼习俗。农历七月初七，孩子沐浴更衣、穿红木屐、拜别花公花婆（儿童保护神）、咬鸡头（象征'出人头地'）、吃甜丸，寓意告别童年、步入成年。",
    "best_viewing": "每年农历七月初七",
    "region": "潮汕全境",
    "level": "省级非遗",
    "tips": "'花园'指儿童时期受到花公花婆保护的花园，15岁要'走出花园'。仪式由家中长辈主持。"
  },
  {
    "name": "潮汕朱泥壶",
    "category": "非遗/传统技艺",
    "description": "潮州枫溪手拉壶，与宜兴紫砂壶齐名。宜兴壶'拍打成型'，潮州壶'手拉成型'——将朱泥放在辘轳上，手工拉出壶身。朱泥含铁量高，烧成红褐色，保温性好，适合泡工夫茶。",
    "best_viewing": "潮州枫溪陶瓷工坊",
    "region": "潮州枫溪",
    "level": "省级非遗",
    "tips": "大师章燕明、谢华的作品具有收藏价值。手感越轻、壶壁越薄越见功力。"
  },
  {
    "name": "凤凰单丛茶制作技艺",
    "category": "非遗/传统技艺",
    "description": "产自潮州凤凰山（海拔约1497米），乌龙茶极品。'一树一香'——鸭屎香（银花香）、蜜兰香、黄枝香、杏仁香等数十种香型。制作需经晒青→晾青→做青→杀青→揉捻→烘焙等复杂工序。",
    "best_viewing": "潮州凤凰镇茶园，春茶采摘季（3-5月）最佳",
    "region": "潮州凤凰镇",
    "level": "省级非遗",
    "tips": "鸭屎香是近年最流行的香型，名字虽俗但香气极雅。春季到凤凰山可体验采茶制茶全过程。"
  },
  {
    "name": "汕头瓶内画",
    "category": "非遗/传统美术",
    "description": "在鼻烟壶内壁作画的微型工艺。用特制的弯头毛笔伸入瓶口（通常仅几毫米），在内壁反向作画。题材涵盖山水、人物、花鸟，极其精细，方寸之间见天地。",
    "best_viewing": "汕头瓶内画博物馆",
    "region": "汕头",
    "level": "省级非遗",
    "tips": "用放大镜观看才能欣赏到细节之美。成品可作艺术品收藏。"
  },
  {
    "name": "营老爷",
    "category": "民俗/节庆",
    "description": "'营老爷'是潮汕最盛大的民俗活动。'老爷'指地方保护神，'营'即巡游。每年农历正月，各村镇将神像请出庙宇，在村中巡游，祈求风调雨顺、合境平安。巡游队伍含英歌舞、潮州大锣鼓、标旗队等，万人空巷。",
    "best_viewing": "农历正月，潮汕各村镇轮流举行",
    "region": "潮汕各地村镇",
    "level": "省级非遗",
    "tips": "汕头澄海区、潮州潮安区最热闹。常见'老爷'：三山国王、妈祖、关帝。跟香是表达虔诚的方式。"
  },
  {
    "name": "元宵赏灯",
    "category": "民俗/节庆",
    "description": "农历正月十五，潮汕各地举办大型灯会。潮州古城灯会（牌坊街+滨江长廊）规模最大，万盏花灯照亮古城。还有猜灯谜、吃汤圆、营灯（游灯）等传统活动。汕头南澳渔灯节以鱼形灯笼为特色。",
    "best_viewing": "农历正月十五",
    "region": "潮州古城、汕头南澳",
    "level": "民俗",
    "tips": "潮州古城灯会是最佳观赏地。建议傍晚到达，逛灯会+吃小吃。灯谜活动互动性强。"
  },
  {
    "name": "端午赛龙舟",
    "category": "民俗/节庆",
    "description": "潮汕龙舟分'游龙'（表演性质，装饰华丽）和'赛龙'（竞速比赛）。赛前有祭江仪式，赛后分'龙舟饭'给村民，寓意吉祥。饶平黄冈河、汕头南澳岛是主要赛场。",
    "best_viewing": "农历五月初五",
    "region": "饶平黄冈河、汕头南澳岛、澄海",
    "level": "民俗",
    "tips": "饶平黄冈河赛龙舟规模最大。端午前后潮汕天气炎热，注意防晒补水。"
  },
  {
    "name": "中秋拜月娘",
    "category": "民俗/节庆",
    "description": "潮汕中秋节俗：庭院设案拜月娘（月亮）、吃朥饼（潮式月饼）、提灯笼。揭阳普宁、汕头澄海等地有'烧塔'习俗——用砖块搭成塔形，内燃柴火，火光冲天，祈求红红火火。",
    "best_viewing": "农历八月十五",
    "region": "潮汕全境，烧塔主要在揭阳普宁、汕头澄海",
    "level": "民俗",
    "tips": "烧塔是中秋夜最壮观的场景，塔越高越旺越吉利。拜月娘的供品包括月饼、水果、芋头。"
  },
  {
    "name": "冬至祭祖",
    "category": "民俗/节庆",
    "description": "潮汕有'冬节大过年'之说——冬至比过年还重要。当天家家祭祖、吃冬至丸（糯米汤圆），'吃了冬至丸就大一岁'。冬至丸有白色和粉红色两种，象征团圆和吉祥。",
    "best_viewing": "农历冬至日（公历12月22日前后）",
    "region": "潮汕全境",
    "level": "民俗",
    "tips": "冬至丸是潮汕冬至最具代表性的食物。冬至前后潮汕人通常会回家团聚祭祖。"
  },
  {
    "name": "时年八节",
    "category": "民俗/节庆体系",
    "description": "潮汕人一年中最重要的八个节日：春节、元宵、清明、端午、中元（七月十五）、中秋、冬至、除夕。每个节日都有特定的祭拜仪式和应节食物，构成潮汕人完整的时间节律。",
    "best_viewing": "全年各节日时段",
    "region": "潮汕全境",
    "level": "民俗",
    "tips": "每个节日都有对应的粿品和祭品。中元节（七月十五）的施孤仪式最为盛大。"
  },
  {
    "name": "侨批文化",
    "category": "文化/历史遗产",
    "description": "海外潮汕华侨寄回家乡的银信合一载体——既是汇款凭证又是家书。记录了数以百万计潮汕人下南洋的奋斗史，饱含家国情怀和亲情牵挂。2013年入选联合国教科文组织世界记忆名录。",
    "best_viewing": "汕头侨批文物馆（国内最大侨批专题博物馆），全年开放",
    "region": "汕头",
    "level": "世界记忆遗产",
    "tips": "侨批文物馆免费参观。每封侨批都是一段感人故事——'批'在潮汕话中指信件。"
  },
  {
    "name": "潮汕话",
    "category": "文化/语言",
    "description": "潮汕话属闽南语分支，保留大量古汉语特征，被称为'古汉语活化石'。有8个声调（普通话仅4个），用潮汕话朗读唐诗宋词更押韵。日常用语：'食饱未'（吃了吗）、'有闲来食茶'（有空来喝茶）、'家己人'（自己人）。",
    "best_viewing": "日常交流即可感受",
    "region": "潮汕全境",
    "level": "文化常识",
    "tips": "'家己人'是潮汕人最核心的身份认同概念。虽然潮汕话难学，但一句'家己人'能拉近距离。"
  },
  {
    "name": "潮汕建筑",
    "category": "文化/建筑",
    "description": "潮汕传统民居体系：'下山虎'（一厅二房，最常见）、'四点金'（二落四合院）、'驷马拖车'（大型府第，三落二天井+护厝）、'百鸟朝凰'（超大规模宅第群）。讲究风水、对称布局和精美嵌瓷木雕装饰。",
    "best_viewing": "潮州古城、汕头老市区、澄海陈慈黉故居",
    "region": "潮汕全境",
    "level": "文化常识",
    "tips": "陈慈黉故居（汕头澄海）是'驷马拖车'的代表，被誉为岭南第一侨宅。汕头小公园骑楼群是民国建筑的代表。"
  },
  {
    "name": "拜老爷",
    "category": "文化/信仰",
    "description": "潮汕人每月初一十五、各种神明诞辰都要'拜老爷'（拜神）。常见神明：天公（玉皇大帝）、妈祖（天后）、三山国王（潮汕本土地方神）、关帝、福德老爷（土地公）、花公花婆（儿童保护神）。祭品丰盛，仪式庄严。",
    "best_viewing": "每月初一十五、神明诞辰日",
    "region": "潮汕全境",
    "level": "文化常识",
    "tips": "三山国王是潮汕本土特有的地方神。妈祖信仰在沿海地区最盛。拜老爷用的粿品通常是最好的。"
  },
  {
    "name": "七样羹",
    "category": "民俗/饮食",
    "description": "正月初七'人日'传统食俗。将七种蔬菜（大菜/芥菜、厚合/百合、芹菜、蒜、春菜、白菜、芥蓝）一起煮成羹。每种蔬菜都有寓意：芹菜=勤劳、蒜=精打细算、大菜=大吉大利、春菜=春意盎然。",
    "best_viewing": "每年农历正月初七",
    "region": "潮汕全境",
    "level": "民俗",
    "tips": "正月初七潮汕家家户户都煮七样羹。寓意吃后新的一年顺顺利利。是潮汕新春食俗的重要组成部分。"
  }
]
